aliyun_iot_device/__init__.py
aliyun_iot_device/root.cer
aliyun_iot_device/http/__init__.py
aliyun_iot_device/http/client.py
aliyun_iot_device/mqtt/__init__.py
aliyun_iot_device/mqtt/client.py
yansongda_aliyun_iot_device-0.6.0.dist-info/LICENSE
yansongda_aliyun_iot_device-0.6.0.dist-info/METADATA
yansongda_aliyun_iot_device-0.6.0.dist-info/WHEEL
yansongda_aliyun_iot_device-0.6.0.dist-info/top_level.txt
yansongda_aliyun_iot_device-0.6.0.dist-info/RECORD
