Metadata-Version: 2.1
Name: yansongda-aliyun-iot-device
Version: 0.6.0
Summary: aliyun iot device sdk
Home-page: https://github.com/yansongda/aliyun-iot-device-python
Author: yansongda
Author-email: me@yansongda.cn
License: UNKNOWN
Project-URL: Source, https://github.com/yansongda/aliyun-iot-device-python
Project-URL: Tracker, https://github.com/yansongda/aliyun-iot-device-python/issues
Keywords: yansongda aliyun iot device
Platform: UNKNOWN
Classifier: Programming Language :: Python :: 3
Classifier: License :: OSI Approved :: MIT License
Classifier: Operating System :: OS Independent
Requires-Python: >=3.0, !=3.0.*, !=3.1.*, !=3.2.*, !=3.3.*
Requires-Dist: paho-mqtt (>=1.3.1)
Requires-Dist: requests (>=2.18.4)
Requires-Dist: cachetools (>=2.1.0)
